{
	"id": "baba841c-fe0f-2927-f365-416166e0c824",
	"name": "Github",
	"values": [
		{
			"key": "base_url",
			"value": "https://api.github.com",
			"enabled": true
		},
		{
			"key": "trending_base_url",
			"value": "https://github-trending-api.now.sh",
			"description": "",
			"enabled": true
		},
		{
			"key": "org",
			"value": "apple",
			"enabled": true
		},
		{
			"key": "owner",
			"value": "khoren93",
			"enabled": true
		},
		{
			"key": "repo",
			"value": "SwiftHub",
			"enabled": true
		},
		{
			"key": "username",
			"value": "khoren93",
			"enabled": true
		},
		{
			"key": "per_page",
			"value": "10",
			"enabled": true
		}
	],
	"_postman_variable_scope": "environment",
	"_postman_exported_at": "2019-08-25T13:44:31.924Z",
	"_postman_exported_using": "Postman/7.5.0"
}